drs/__init__.py
drs/drs.py
drs-2.0.1.dist-info/METADATA
drs-2.0.1.dist-info/WHEEL
drs-2.0.1.dist-info/top_level.txt
drs-2.0.1.dist-info/RECORD
