Metadata-Version: 2.4
Name: DRS
Version: 2.0.1
Summary: DEPRECATED. An algorithm which attempted to generate uniformly sampled random vectors which sum to a given value, but could fail with uniformity. Use ConvolutionalFixedSum instead.
Author-email: David Griffin <dgdguk@gmail.com>
License-Expression: BSD-3-Clause
Project-URL: Homepage, https://github.com/dgdguk/drs
Project-URL: Issues, https://github.com/dgdguk/drs/issues
Classifier: Programming Language :: Python :: 3
Classifier: Operating System :: OS Independent
Requires-Python: >=3.7
Requires-Dist: numpy>=2.2.5
Requires-Dist: scipy>=1.15
Requires-Dist: cffi>=1.17
